metric_helper/__init__.py
metric_helper/apps.py
metric_helper/base.py
metric_helper/conf.py
metric_helper/connections.py
metric_helper/dataset.py
metric_helper/exceptions.py
metric_helper/logging.py
metric_helper/registry.py
metric_helper/timezone.py
metric_helper/utils.py
tests/__init__.py
tests/load.py
tests/test_counter.py
tests/test_dataset.py
tests/test_gauge.py
tests/test_gauge_ts.py
tests/test_init.py
tests/test_pos_gauge.py
tests/test_pos_gauge_ts.py
tests/test_tdigest.py
tests/test_timeseries.py
tests/test_timezone.py
redis_metric_helper-0.7.6.dist-info/LICENSE
redis_metric_helper-0.7.6.dist-info/METADATA
redis_metric_helper-0.7.6.dist-info/WHEEL
redis_metric_helper-0.7.6.dist-info/top_level.txt
redis_metric_helper-0.7.6.dist-info/RECORD
