Metadata-Version: 2.1
Name: redis-metric-helper
Version: 0.7.6
Summary: A helper to make writing/reading metrics to Redis more convenient.
Author: Armandt van Zyl
Classifier: Environment :: Web Environment
Classifier: Intended Audience :: Developers
Classifier: Programming Language :: Python
Classifier: Programming Language :: Python :: 3
Classifier: Programming Language :: Python :: 3.8
Classifier: Programming Language :: Python :: 3 :: Only
Classifier: Topic :: Internet :: WWW/HTTP
Requires-Python: >=3.8
License-File: LICENSE
Requires-Dist: redis
Requires-Dist: pytz
